LICENSE
MANIFEST.in
README.rst
setup.py
sphinx_theme_pd/__init__.py
sphinx_theme_pd/layout.html
sphinx_theme_pd/page.html
sphinx_theme_pd/theme.conf
sphinx_theme_pd.egg-info/PKG-INFO
sphinx_theme_pd.egg-info/SOURCES.txt
sphinx_theme_pd.egg-info/dependency_links.txt
sphinx_theme_pd.egg-info/not-zip-safe
sphinx_theme_pd.egg-info/top_level.txt
sphinx_theme_pd/static/pd.css
sphinx_theme_pd/static/pd.js