Metadata-Version: 1.1
Name: sphinx-theme-pd
Version: 0.0.8
Summary: Material Design theme for Sphinx.
Home-page: https://github.com/iktakahiro/sphinx_theme_pd
Author: Takahiro Ikeuchi @iktakahiro
Author-email: takahiro.ikeuchi@gmail.com
License: MIT
Platform: UNKNOWN
Classifier: Environment :: Console
Classifier: Environment :: Web Environment
Classifier: Intended Audience :: Developers
Classifier: Programming Language :: Python :: 2.7
Classifier: Programming Language :: Python :: 3
Classifier: Topic :: Documentation
Classifier: Topic :: Software Development :: Documentation
